README.txt
setup.py
point_tracker/__init__.py
point_tracker/add.png
point_tracker/add_cell.png
point_tracker/algo.py
point_tracker/algo_session.py
point_tracker/alignmentdlg.py
point_tracker/alignmentdlg.ui
point_tracker/convolution_timing.py
point_tracker/copy_progress.ui
point_tracker/debug.py
point_tracker/delete.png
point_tracker/deletedlg.ui
point_tracker/down.png
point_tracker/draw_velocities.py
point_tracker/editmarkersdlg.py
point_tracker/editmarkersdlg.ui
point_tracker/editresdlg.py
point_tracker/editresdlg.ui
point_tracker/finetune.png
point_tracker/geometry.py
point_tracker/growth_algo.py
point_tracker/growth_computation.py
point_tracker/growth_computation.ui
point_tracker/growth_computation_methods.py
point_tracker/gtk-zoom-100.png
point_tracker/gtk-zoom-fit.png
point_tracker/gtk-zoom-in.png
point_tracker/gtk-zoom-out.png
point_tracker/icon.png
point_tracker/icon512.png
point_tracker/icons.qrc
point_tracker/icons_rc.py
point_tracker/image_cache.py
point_tracker/insert-link.png
point_tracker/left.png
point_tracker/lifespan.ui
point_tracker/link.png
point_tracker/link_broken.png
point_tracker/link_broken_macos.png
point_tracker/link_macos.png
point_tracker/loader.py
point_tracker/move.png
point_tracker/move_pts.png
point_tracker/new.png
point_tracker/next.png
point_tracker/normcross.py
point_tracker/open.png
point_tracker/options.png
point_tracker/palette.png
point_tracker/parameters.py
point_tracker/parametersdlg.py
point_tracker/parametersdlg.ui
point_tracker/path.py
point_tracker/plot_preview.py
point_tracker/plot_preview.ui
point_tracker/plotting_methods.py
point_tracker/plottingdlg.py
point_tracker/plottingdlg.ui
point_tracker/plottingoptionsdlg.py
point_tracker/plottingoptionsdlg.ui
point_tracker/prev.png
point_tracker/project.py
point_tracker/python2.py
point_tracker/qtransferfunctionviewer.py
point_tracker/quit.png
point_tracker/redo.png
point_tracker/reload.png
point_tracker/remove.png
point_tracker/remove_cell.png
point_tracker/right.png
point_tracker.egg-info/PKG-INFO
point_tracker.egg-info/SOURCES.txt
point_tracker.egg-info/dependency_links.txt
point_tracker.egg-info/entry_points.txt
point_tracker.egg-info/pbr.json
point_tracker.egg-info/requires.txt
point_tracker.egg-info/top_level.txt
