Metadata-Version: 1.1
Name: point-tracker
Version: 0.7.6
Summary: Track points and cells on 2D tissues over time.
Home-page: ['https://github.com/PierreBdR/point_tracker']
Author: Pierre Barbier de Reuille
Author-email: pierre.barbierdereuille@gmail.com
License: LICENSE
Platform: Linux
Platform: Windows
Platform: MacOS
Classifier: Development Status :: 5 - Production/Stable
Classifier: Environment :: X11 Applications :: Qt
Classifier: Intended Audience :: Science/Research
Classifier: License :: OSI Approved :: GNU General Public License v2 or later (GPLv2+)
Classifier: Natural Language :: English
Classifier: Operating System :: MacOS :: MacOS X
Classifier: Operating System :: Microsoft :: Windows
Classifier: Operating System :: POSIX :: Linux
Classifier: Programming Language :: Python :: 2.7
Classifier: Programming Language :: Python :: 3.3
Classifier: Programming Language :: Python :: 3.4
Classifier: Topic :: Scientific/Engineering
Classifier: Topic :: Scientific/Engineering :: Visualization
